MANIFEST.in
README.rst
RELEASE-VERSION
setup.cfg
setup.py
gitpy_versioning/__init__.py
gitpy_versioning/test_gitpy_versioning.py
sleepwalker/__init__.py
sleepwalker/connection.py
sleepwalker/datarep.py
sleepwalker/exceptions.py
sleepwalker/service.py
sleepwalker.egg-info/PKG-INFO
sleepwalker.egg-info/SOURCES.txt
sleepwalker.egg-info/dependency_links.txt
sleepwalker.egg-info/requires.txt
sleepwalker.egg-info/top_level.txt
test/test_basic.py
test/test_bookstore.py
test/test_connection.py
test/test_crossref.py
test/test_datarep.py
test/test_exceptions.py
test/test_service.py